troika/__init__.py
troika/__main__.py
troika/cli.py
troika/components.py
troika/config.py
troika/connection.py
troika/controller.py
troika/directives.py
troika/generator.py
troika/hook.py
troika/log.py
troika/parser.py
troika/site.py
troika/utils.py
troika/connections/__init__.py
troika/connections/base.py
troika/connections/local.py
troika/connections/ssh.py
troika/controllers/__init__.py
troika/controllers/base.py
troika/hooks/__init__.py
troika/hooks/base.py
troika/hooks/common.py
troika/hooks/ecflow.py
troika/sites/__init__.py
troika/sites/base.py
troika/sites/direct.py
troika/sites/group.py
troika/sites/pbs.py
troika/sites/sge.py
troika/sites/slurm.py
troika/translators/__init__.py
troika/translators/base.py
troika/translators/common.py
troika/translators/resources.py
troika-0.2.6.dist-info/LICENSE
troika-0.2.6.dist-info/METADATA
troika-0.2.6.dist-info/WHEEL
troika-0.2.6.dist-info/entry_points.txt
troika-0.2.6.dist-info/top_level.txt
troika-0.2.6.dist-info/RECORD
