Metadata-Version: 2.2
Name: troika
Version: 0.2.6
Summary: Submit, monitor and kill jobs on remote systems
Author-email: Olivier Iffrig <software.support@ecmwf.int>
License: Apache Software License 2.0
Project-URL: Homepage, https://github.com/ecmwf/troika
Classifier: Development Status :: 4 - Beta
Classifier: License :: OSI Approved :: Apache Software License
Classifier: Operating System :: POSIX
Classifier: Programming Language :: Python :: 3.8
Classifier: Topic :: System :: Distributed Computing
Requires-Python: >=3.8
License-File: LICENSE
Requires-Dist: pyyaml
Provides-Extra: docs
Requires-Dist: Sphinx; extra == "docs"
Provides-Extra: tests
Requires-Dist: pytest; extra == "tests"
